vaft/__init__.py
vaft/version.py
vaft/code/__init__.py
vaft/code/chease.py
vaft/code/efit.py
vaft/code/gpec.py
vaft/database/__init__.py
vaft/database/ods.py
vaft/database/raw.py
vaft/formula/__init__.py
vaft/formula/equilibrium.py
vaft/formula/green.py
vaft/formula/vacuum.py
vaft/formula/virial.py
vaft/machine_mapping/__init__.py
vaft/machine_mapping/from_file.py
vaft/machine_mapping/from_raw_database.py
vaft/machine_mapping/static.py
vaft/omas/__init__.py
vaft/omas/formula_wrapper.py
vaft/omas/general.py
vaft/omas/process_wrapper.py
vaft/omas/sample.py
vaft/omas/update.py
vaft/plot/__init__.py
vaft/plot/animation.py
vaft/plot/onedim.py
vaft/plot/time.py
vaft/plot/topview.py
vaft/plot/twodim.py
vaft/process/__init__.py
vaft/process/default.py
vaft/process/electromagnetics.py
vaft/process/equilibrium.py
vaft/process/magnetics.py
vaft/process/profile.py
vaft/process/signal_processing.py
vaft/profile/__init__.py
vaft/profile/gfile.py
vaft/profile/profile.py
vaft-0.1.dist-info/METADATA
vaft-0.1.dist-info/WHEEL
vaft-0.1.dist-info/top_level.txt
vaft-0.1.dist-info/RECORD
