Metadata-Version: 2.1
Name: vaft
Version: 0.1
Summary: Versatile Analytical Framework for Tokamak
Home-page: https://github.com/VEST-Tokamak/vaft
Author: satelite2517, Hikitonic
Author-email: satelite2517@snu.ac.kr, peppertonic18@snu.ac.kr
Requires-Dist: h5py
Requires-Dist: numpy
Requires-Dist: uncertainties
Requires-Dist: omas
Requires-Dist: matplotlib
Provides-Extra: dev
Requires-Dist: pytest ; extra == 'dev'
Requires-Dist: black ; extra == 'dev'
Requires-Dist: flake8 ; extra == 'dev'
